industryandcovid.py
industryandcovid-0.0.7.dist-info/LICENSE
industryandcovid-0.0.7.dist-info/METADATA
industryandcovid-0.0.7.dist-info/WHEEL
industryandcovid-0.0.7.dist-info/entry_points.txt
industryandcovid-0.0.7.dist-info/top_level.txt
industryandcovid-0.0.7.dist-info/RECORD
