Metadata-Version: 2.1
Name: industryandcovid
Version: 0.0.7
Summary: This project will compare amusement park sales with Internet industry sales and the number of people infected with COVID.
Home-page: https://github.com/ritakei/industryandcovid
Author: rinko takei
Author-email: rtakei@sciencepark.co.jp
License: UNKNOWN
Project-URL: Bug Tracker, https://github.com/ritakei/industryandcovid
Platform: UNKNOWN
Classifier: Programming Language :: Python :: 3
Classifier: License :: OSI Approved :: MIT License
Classifier: Operating System :: OS Independent
Requires-Python: >=3.8.5
License-File: LICENSE
